{
  "players": [
    {
      "token": "?",
      "name": "Rubencio",
      "record": 19
    },
    {
      "token": "?",
      "name": "vijomc",
      "record": 0
    },
    {
      "token": "1/null",
      "name": "Sarandonga",
      "record": 17
    },
    {
      "token": "[Dfhm92JaGnlLp15ahFJpfe]",
      "name": "Calimocho",
      "record": 14
    },
    {
      "token": "1:null:Android:emulator_arm64",
      "name": "User",
      "record": 2
    },
    {
      "token": "",
      "name": "Rubencio",
      "record": 5
    }
  ]
}